mmds/__init__.py
mmds/dataset.py
mmds/exceptions.py
mmds/sample.py
mmds/version.py
mmds/modalities/__init__.py
mmds/modalities/f0.py
mmds/modalities/ge2e.py
mmds/modalities/modality.py
mmds/modalities/npz.py
mmds/modalities/rgb.py
mmds/modalities/rgbs.py
mmds/modalities/spec.py
mmds/modalities/traits.py
mmds/modalities/ts.py
mmds/modalities/wav.py
mmds/utils/__init__.py
mmds/utils/spectrogram.py
mmds/utils/yin.py
mmds-0.0.1.dev20220108134301.dist-info/LICENSE
mmds-0.0.1.dev20220108134301.dist-info/METADATA
mmds-0.0.1.dev20220108134301.dist-info/WHEEL
mmds-0.0.1.dev20220108134301.dist-info/top_level.txt
mmds-0.0.1.dev20220108134301.dist-info/RECORD
