Metadata-Version: 2.1
Name: mmds
Version: 0.0.1.dev20220108134301
Summary: MMDS: A general-purpose multimodal dataset wrapper.
Home-page: https://github.com/enhuiz/mmds
Author: enhuiz
Author-email: niuzhe.nz@outlook.com
License: UNKNOWN
Platform: UNKNOWN
Requires-Python: >=3.9.0
License-File: LICENSE
Requires-Dist: attrs
